{
  "warnings": [
    {
      "file": "/Users/justin.fitzgerald/Code/tealium-swift-v3/tealium-prism/core/API/Settings/Mappings.swift",
      "line": 11,
      "symbol": "MappingsBuilder",
      "symbol_kind": "source.lang.swift.decl.class",
      "warning": "undocumented"
    },
    {
      "file": "/Users/justin.fitzgerald/Code/tealium-swift-v3/tealium-prism/core/API/Settings/Mappings.swift",
      "line": 97,
      "symbol": "Mappings.init()",
      "symbol_kind": "source.lang.swift.decl.function.method.instance",
      "warning": "undocumented"
    }
  ],
  "source_directory": "/Users/justin.fitzgerald/Code/tealium-swift-v3"
}